AUTHORS.rst
CHANGELOG.rst
LICENSE
MANIFEST.in
README.rst
setup.py
django_scaler.egg-info/PKG-INFO
django_scaler.egg-info/SOURCES.txt
django_scaler.egg-info/dependency_links.txt
django_scaler.egg-info/not-zip-safe
django_scaler.egg-info/requires.txt
django_scaler.egg-info/top_level.txt
scaler/__init__.py
scaler/middleware.py
scaler/models.py
scaler/settings.py
scaler/tests.py
scaler/urls.py
scaler/templates/scaler/server_busy.html
scaler/templates/scaler/test.html
scaler/templatetags/__init__.py
scaler/templatetags/__init__.pyc
scaler/templatetags/scaler_tags.py
scaler/templatetags/scaler_tags.pyc