Metadata-Version: 1.0
Name: django-scaler
Version: 0.2
Summary: Degrade gracefully by automatically replacing heavy pages with static pages while a server is taking strain.
Home-page: http://github.com/praekelt/django-scaler
Author: Praekelt Foundation
Author-email: dev@praekelt.com
License: BSD
Platform: UNKNOWN
Classifier: Programming Language :: Python
Classifier: License :: OSI Approved :: BSD License
Classifier: Operating System :: OS Independent
Classifier: Framework :: Django
Classifier: Intended Audience :: Developers
Classifier: Topic :: Internet :: WWW/HTTP :: Dynamic Content
